{
	"extends": [
		"tslint:latest",
		"tslint-react",
		"tslint-eslint-rules"
	],
	"rules": {
		"no-constant-condition": false, // tslint-eslint-rules says this
		"max-line-length": [true, 101],
		"no-unused-expression": true,
		"no-duplicate-variable": true,
		"no-duplicate-imports": false,
		"no-unused-variable": true,
		"no-shadowed-variable": false,
		"no-submodule-imports": false,
		"curly": true,
		"class-name": true,
		"semicolon": [
			true,
			"always"
		],
		"triple-equals": true,
		"variable-name": false,
		"interface-name": [
			"never-prefix"
		],
		"no-consecutive-blank-lines": [
			true,
			2
		],
		"array-type": [
			"generic"
		],
		"no-object-literal-type-assertion": false,
		"object-literal-sort-keys": false,
		"object-literal-key-quotes": [false],
		"arrow-parens": [
			true,
			"ban-single-arg-parens"
		],
		"member-access": false,
		"no-console": false,
		"jsx-wrap-multiline": false,
		"jsx-no-multiline-js": false,
		"jsx-alignment": false,
		"jsx-no-lambda": false,
		"max-classes-per-file": false,
		"quotemark": [
			"avoid-escape"
		],
		"space-before-function-paren": false,
		"type-literal-delimiter": true,
		"trailing-comma": [
			true,
			{
				"multiline": {
					"objects": "always"
				},
				"singleline": "never"
			}
		]
	}
}
